example/example1/main.py
example/example2/main.py
gamuLogger/__init__.py
gamuLogger/argparse_config.py
gamuLogger/condition.py
gamuLogger/config.py
gamuLogger/custom_types.py
gamuLogger/function.py
gamuLogger/gamu_logger.py
gamuLogger/module.py
gamuLogger/regex.py
gamuLogger/targets.py
gamuLogger/utils.py
gamulogger-3.2.4.dist-info/licenses/LICENSE
tests/argparse_config_test.py
tests/condition_test.py
tests/config_test.py
tests/custom_types_test.py
tests/function_test.py
tests/gamu_logger_test.py
tests/module_test.py
tests/targets_test.py
tests/utils_test.py
gamulogger-3.2.4.dist-info/METADATA
gamulogger-3.2.4.dist-info/WHEEL
gamulogger-3.2.4.dist-info/top_level.txt
gamulogger-3.2.4.dist-info/RECORD
