Metadata-Version: 2.4
Name: gamuLogger
Version: 3.2.4
Summary: A Logging library for Python.
Author-email: Antoine Buirey <antoine.buirey@gmail.com>
License-Expression: MIT
Project-URL: Homepage, https://github.com/T0ine34/gamuLogger
Project-URL: Issues, https://github.com/T0ine34/gamuLogger/issues
Keywords: logger,logging,log,python,gamuLogger,trace
Classifier: Programming Language :: Python :: 3
Classifier: Programming Language :: Python :: 3.8
Classifier: Programming Language :: Python :: 3.9
Classifier: Programming Language :: Python :: 3.10
Classifier: Programming Language :: Python :: 3.11
Classifier: Programming Language :: Python :: 3.12
Classifier: Programming Language :: Python :: 3.13
Classifier: Programming Language :: Python :: Implementation :: CPython
Classifier: Operating System :: OS Independent
Classifier: Topic :: System :: Logging
Classifier: Topic :: Software Development :: Libraries :: Python Modules
Classifier: Intended Audience :: Developers
Classifier: Development Status :: 5 - Production/Stable
Classifier: Natural Language :: English
Requires-Python: >=3.12
License-File: LICENSE
Dynamic: license-file
